odoo/addons/mrp_production_operation_injection/README.rst
odoo/addons/mrp_production_operation_injection/__init__.py
odoo/addons/mrp_production_operation_injection/__manifest__.py
odoo/addons/mrp_production_operation_injection/i18n/es.po
odoo/addons/mrp_production_operation_injection/i18n/it.po
odoo/addons/mrp_production_operation_injection/i18n/mrp_production_operation_injection.pot
odoo/addons/mrp_production_operation_injection/models/__init__.py
odoo/addons/mrp_production_operation_injection/models/mrp_production.py
odoo/addons/mrp_production_operation_injection/models/mrp_workorder.py
odoo/addons/mrp_production_operation_injection/readme/CONTRIBUTORS.rst
odoo/addons/mrp_production_operation_injection/readme/DESCRIPTION.rst
odoo/addons/mrp_production_operation_injection/security/ir.model.access.csv
odoo/addons/mrp_production_operation_injection/static/description/icon.png
odoo/addons/mrp_production_operation_injection/static/description/index.html
odoo/addons/mrp_production_operation_injection/tests/__init__.py
odoo/addons/mrp_production_operation_injection/tests/test_mrp_production_inject_operation.py
odoo/addons/mrp_production_operation_injection/views/mrp_production.xml
odoo/addons/mrp_production_operation_injection/views/mrp_workorder.xml
odoo/addons/mrp_production_operation_injection/wizard/__init__.py
odoo/addons/mrp_production_operation_injection/wizard/mrp_workorder_injector.py
odoo/addons/mrp_production_operation_injection/wizard/mrp_workorder_injector.xml
odoo_addon_mrp_production_operation_injection-15.0.1.0.0.7.dist-info/METADATA
odoo_addon_mrp_production_operation_injection-15.0.1.0.0.7.dist-info/WHEEL
odoo_addon_mrp_production_operation_injection-15.0.1.0.0.7.dist-info/top_level.txt
odoo_addon_mrp_production_operation_injection-15.0.1.0.0.7.dist-info/RECORD
