Metadata-Version: 2.1
Name: odoo-addon-mrp_production_operation_injection
Version: 15.0.1.0.0.7
Summary: Adds an existing operation from the Bill of Material
Home-page: https://github.com/OCA/manufacture
Author: Camptocamp, Odoo Community Association (OCA)
Author-email: support@odoo-community.org
License: AGPL-3
Classifier: Programming Language :: Python
Classifier: Framework :: Odoo
Classifier: Framework :: Odoo :: 15.0
Classifier: License :: OSI Approved :: GNU Affero General Public License v3
Classifier: Development Status :: 4 - Beta
Requires-Python: >=3.8
Requires-Dist: odoo-addon-mrp-workorder-sequence<15.1dev,>=15.0dev
Requires-Dist: odoo<15.1dev,>=15.0a
